osdu_api/__init__.py
osdu_api/constants.py
osdu_api/version.py
osdu_api/auth/__init__.py
osdu_api/auth/authorization.py
osdu_api/auth/refresh_token.py
osdu_api/clients/__init__.py
osdu_api/clients/base_client.py
osdu_api/clients/crs_catalog/__init__.py
osdu_api/clients/crs_catalog/crs_catalog_client.py
osdu_api/clients/crs_conversion/__init__.py
osdu_api/clients/crs_conversion/crs_conversion_client.py
osdu_api/clients/data_workflow/__init__.py
osdu_api/clients/data_workflow/data_workflow_client.py
osdu_api/clients/data_workflow/data_workflow_scheduling_client.py
osdu_api/clients/dataset/__init__.py
osdu_api/clients/dataset/dataset_dms_client.py
osdu_api/clients/dataset/dataset_registry_client.py
osdu_api/clients/entitlements/__init__.py
osdu_api/clients/entitlements/entitlements_client.py
osdu_api/clients/ingestion_workflow/__init__.py
osdu_api/clients/ingestion_workflow/ingestion_workflow_client.py
osdu_api/clients/legal/__init__.py
osdu_api/clients/legal/legal_client.py
osdu_api/clients/partition/__init__.py
osdu_api/clients/partition/partition_client.py
osdu_api/clients/schema/__init__.py
osdu_api/clients/schema/schema_client.py
osdu_api/clients/search/__init__.py
osdu_api/clients/search/search_client.py
osdu_api/clients/storage/__init__.py
osdu_api/clients/storage/record_client.py
osdu_api/clients/storage/schema_client.py
osdu_api/clients/unit/__init__.py
osdu_api/clients/unit/unit_client.py
osdu_api/configuration/__init__.py
osdu_api/configuration/base_config_manager.py
osdu_api/configuration/config_manager.py
osdu_api/examples/create_and_search_example.py
osdu_api/examples/data_workflow_examples.py
osdu_api/examples/dataset_example.py
osdu_api/examples/ingestion_workflow_examples.py
osdu_api/examples/legal_examples.py
osdu_api/examples/search_with_cursor_example.py
osdu_api/exceptions/__init__.py
osdu_api/exceptions/exceptions.py
osdu_api/model/__init__.py
osdu_api/model/acl.py
osdu_api/model/base.py
osdu_api/model/http_method.py
osdu_api/model/record.py
osdu_api-1.0.3.dist-info/licenses/LICENSE
osdu_api-1.0.3.dist-info/METADATA
osdu_api-1.0.3.dist-info/WHEEL
osdu_api-1.0.3.dist-info/top_level.txt
osdu_api-1.0.3.dist-info/RECORD
