Metadata-Version: 2.4
Name: osdu_api
Version: 1.0.3
Summary: A package to interface with OSDU microservices
Author: OSDU team
License-Expression: Apache-2.0
Project-URL: Homepage, https://community.opengroup.org/osdu/platform/system/sdks/common-python-sdk
Classifier: Programming Language :: Python :: 3
Classifier: Operating System :: OS Independent
Requires-Python: >=3.11
License-File: LICENSE
Requires-Dist: requests>=2.32.3
Requires-Dist: tenacity>=9.1.2
Requires-Dist: httpx>=0.28.1
Provides-Extra: dev
Requires-Dist: mock==5.2.0; extra == "dev"
Requires-Dist: pytest==8.3.5; extra == "dev"
Requires-Dist: pytest-mock==3.14.0; extra == "dev"
Requires-Dist: responses==0.25.7; extra == "dev"
Requires-Dist: twine==6.1.0; extra == "dev"
Requires-Dist: jsonschema==4.23.0; extra == "dev"
Requires-Dist: toposort==1.10; extra == "dev"
Provides-Extra: azure
Requires-Dist: azure-identity==1.22.0; extra == "azure"
Requires-Dist: azure-keyvault==4.2.0; extra == "azure"
Requires-Dist: azure-storage-blob==12.25.0; extra == "azure"
Provides-Extra: gc
Requires-Dist: google-auth==2.40.1; extra == "gc"
Requires-Dist: google-cloud-storage==3.1.0; extra == "gc"
Provides-Extra: ibm
Requires-Dist: boto3==1.38.13; extra == "ibm"
Requires-Dist: keycloak-client==0.15.4; extra == "ibm"
Provides-Extra: common
Requires-Dist: azure-identity==1.22.0; extra == "common"
Requires-Dist: azure-keyvault==4.2.0; extra == "common"
Requires-Dist: azure-storage-blob==12.25.0; extra == "common"
Requires-Dist: google-auth==2.40.1; extra == "common"
Requires-Dist: google-cloud-storage==3.1.0; extra == "common"
Requires-Dist: boto3==1.38.12; extra == "common"
Requires-Dist: keycloak-client==0.15.4; extra == "common"
Dynamic: license-file
